<?xml version="1.0" encoding="UTF-8" ?>
<!DOCTYPE mapper PUBLIC "-//mybatis.org//DTD Mapper 3.0//EN" "http://mybatis.org/dtd/mybatis-3-mapper.dtd" >
<mapper namespace="com.cul.culsite.dao.MGoodsDTOMapper" >
  <resultMap id="BaseResultMap" type="com.cul.culsite.dto.MGoodsDTO" >
    <!--
      WARNING - @mbggenerated
      This element is automatically generated by MyBatis Generator, do not modify.
    -->
    <id column="MGC_ID" property="mgcId" jdbcType="VARCHAR" />
    <result column="MGC_ISSUER_ID" property="mgcIssuerId" jdbcType="VARCHAR" />
    <result column="MGC_TYPE" property="mgcType" jdbcType="VARCHAR" />
    <result column="MGC_CODE" property="mgcCode" jdbcType="VARCHAR" />
    <result column="MGC_NAME" property="mgcName" jdbcType="VARCHAR" />
    <result column="MGC_URL" property="mgcUrl" jdbcType="VARCHAR" />
    <result column="MGC_PARENT_NO" property="mgcParentNo" jdbcType="VARCHAR" />
    <result column="MGC_STATUS" property="mgcStatus" jdbcType="VARCHAR" />
    <result column="CREATE_USER" property="createUser" jdbcType="VARCHAR" />
    <result column="CREATE_TIMESTAMP" property="createTimestamp" jdbcType="DATE" />
    <result column="UPDATE_USER" property="updateUser" jdbcType="VARCHAR" />
    <result column="UPDATE_TIMESTAMP" property="updateTimestamp" jdbcType="DATE" />
    <result column="PUBLISH_AREA" property="publishArea" jdbcType="VARCHAR" />
    <result column="PUBLISH_ISSUER" property="publishIssuer" jdbcType="VARCHAR" />
  </resultMap>
  <sql id="Example_Where_Clause" >
    <!--
      WARNING - @mbggenerated
      This element is automatically generated by MyBatis Generator, do not modify.
    -->
    <where >
      <foreach collection="oredCriteria" item="criteria" separator="or" >
        <if test="criteria.valid" >
          <trim prefix="(" suffix=")" prefixOverrides="and" >
            <foreach collection="criteria.criteria" item="criterion" >
              <choose >
                <when test="criterion.noValue" >
                  and ${criterion.condition}
                </when>
                <when test="criterion.singleValue" >
                  and ${criterion.condition} #{criterion.value}
                </when>
                <when test="criterion.betweenValue" >
                  and ${criterion.condition} #{criterion.value} and #{criterion.secondValue}
                </when>
                <when test="criterion.listValue" >
                  and ${criterion.condition}
                  <foreach collection="criterion.value" item="listItem" open="(" close=")" separator="," >
                    #{listItem}
                  </foreach>
                </when>
              </choose>
            </foreach>
          </trim>
        </if>
      </foreach>
    </where>
  </sql>
  <sql id="Update_By_Example_Where_Clause" >
    <!--
      WARNING - @mbggenerated
      This element is automatically generated by MyBatis Generator, do not modify.
    -->
    <where >
      <foreach collection="example.oredCriteria" item="criteria" separator="or" >
        <if test="criteria.valid" >
          <trim prefix="(" suffix=")" prefixOverrides="and" >
            <foreach collection="criteria.criteria" item="criterion" >
              <choose >
                <when test="criterion.noValue" >
                  and ${criterion.condition}
                </when>
                <when test="criterion.singleValue" >
                  and ${criterion.condition} #{criterion.value}
                </when>
                <when test="criterion.betweenValue" >
                  and ${criterion.condition} #{criterion.value} and #{criterion.secondValue}
                </when>
                <when test="criterion.listValue" >
                  and ${criterion.condition}
                  <foreach collection="criterion.value" item="listItem" open="(" close=")" separator="," >
                    #{listItem}
                  </foreach>
                </when>
              </choose>
            </foreach>
          </trim>
        </if>
      </foreach>
    </where>
  </sql>
  <sql id="Base_Column_List" >
    <!--
      WARNING - @mbggenerated
      This element is automatically generated by MyBatis Generator, do not modify.
    -->
    MGC_ID, MGC_ISSUER_ID, MGC_TYPE, MGC_CODE, MGC_NAME, MGC_URL, MGC_PARENT_NO, MGC_STATUS, 
    CREATE_USER, CREATE_TIMESTAMP, UPDATE_USER, UPDATE_TIMESTAMP, PUBLISH_AREA, PUBLISH_ISSUER
  </sql>
  <select id="selectByExample" resultMap="BaseResultMap" parameterType="com.cul.culsite.dto.MGoodsDTOCriteria" >
    <!--
      WARNING - @mbggenerated
      This element is automatically generated by MyBatis Generator, do not modify.
    -->
    select
    <if test="distinct" >
      distinct
    </if>
    <include refid="Base_Column_List" />
    from M_GOODS_CAT
    <if test="_parameter != null" >
      <include refid="Example_Where_Clause" />
    </if>
    <if test="orderByClause != null" >
      order by ${orderByClause}
    </if>
  </select>
  <select id="selectByPrimaryKey" resultMap="BaseResultMap" parameterType="java.lang.String" >
    <!--
      WARNING - @mbggenerated
      This element is automatically generated by MyBatis Generator, do not modify.
    -->
    select 
    <include refid="Base_Column_List" />
    from M_GOODS_CAT
    where MGC_ID = #{mgcId,jdbcType=VARCHAR}
  </select>
  <delete id="deleteByPrimaryKey" parameterType="java.lang.String" >
    <!--
      WARNING - @mbggenerated
      This element is automatically generated by MyBatis Generator, do not modify.
    -->
    delete from M_GOODS_CAT
    where MGC_ID = #{mgcId,jdbcType=VARCHAR}
  </delete>
  <delete id="deleteByExample" parameterType="com.cul.culsite.dto.MGoodsDTOCriteria" >
    <!--
      WARNING - @mbggenerated
      This element is automatically generated by MyBatis Generator, do not modify.
    -->
    delete from M_GOODS_CAT
    <if test="_parameter != null" >
      <include refid="Example_Where_Clause" />
    </if>
  </delete>
  <insert id="insert" parameterType="com.cul.culsite.dto.MGoodsDTO" >
    <!--
      WARNING - @mbggenerated
      This element is automatically generated by MyBatis Generator, do not modify.
    -->
    insert into M_GOODS_CAT (MGC_ID, MGC_ISSUER_ID, MGC_TYPE, 
      MGC_CODE, MGC_NAME, MGC_URL, 
      MGC_PARENT_NO, MGC_STATUS, CREATE_USER, 
      CREATE_TIMESTAMP, UPDATE_USER, UPDATE_TIMESTAMP, 
      PUBLISH_AREA, PUBLISH_ISSUER)
    values (#{mgcId,jdbcType=VARCHAR}, #{mgcIssuerId,jdbcType=VARCHAR}, #{mgcType,jdbcType=VARCHAR}, 
      #{mgcCode,jdbcType=VARCHAR}, #{mgcName,jdbcType=VARCHAR}, #{mgcUrl,jdbcType=VARCHAR}, 
      #{mgcParentNo,jdbcType=VARCHAR}, #{mgcStatus,jdbcType=VARCHAR}, #{createUser,jdbcType=VARCHAR}, 
      #{createTimestamp,jdbcType=DATE}, #{updateUser,jdbcType=VARCHAR}, #{updateTimestamp,jdbcType=DATE}, 
      #{publishArea,jdbcType=VARCHAR}, #{publishIssuer,jdbcType=VARCHAR})
  </insert>
  <insert id="insertSelective" parameterType="com.cul.culsite.dto.MGoodsDTO" >
    <!--
      WARNING - @mbggenerated
      This element is automatically generated by MyBatis Generator, do not modify.
    -->
    insert into M_GOODS_CAT
    <trim prefix="(" suffix=")" suffixOverrides="," >
      <if test="mgcId != null" >
        MGC_ID,
      </if>
      <if test="mgcIssuerId != null" >
        MGC_ISSUER_ID,
      </if>
      <if test="mgcType != null" >
        MGC_TYPE,
      </if>
      <if test="mgcCode != null" >
        MGC_CODE,
      </if>
      <if test="mgcName != null" >
        MGC_NAME,
      </if>
      <if test="mgcUrl != null" >
        MGC_URL,
      </if>
      <if test="mgcParentNo != null" >
        MGC_PARENT_NO,
      </if>
      <if test="mgcStatus != null" >
        MGC_STATUS,
      </if>
      <if test="createUser != null" >
        CREATE_USER,
      </if>
      <if test="createTimestamp != null" >
        CREATE_TIMESTAMP,
      </if>
      <if test="updateUser != null" >
        UPDATE_USER,
      </if>
      <if test="updateTimestamp != null" >
        UPDATE_TIMESTAMP,
      </if>
      <if test="publishArea != null" >
        PUBLISH_AREA,
      </if>
      <if test="publishIssuer != null" >
        PUBLISH_ISSUER,
      </if>
    </trim>
    <trim prefix="values (" suffix=")" suffixOverrides="," >
      <if test="mgcId != null" >
        #{mgcId,jdbcType=VARCHAR},
      </if>
      <if test="mgcIssuerId != null" >
        #{mgcIssuerId,jdbcType=VARCHAR},
      </if>
      <if test="mgcType != null" >
        #{mgcType,jdbcType=VARCHAR},
      </if>
      <if test="mgcCode != null" >
        #{mgcCode,jdbcType=VARCHAR},
      </if>
      <if test="mgcName != null" >
        #{mgcName,jdbcType=VARCHAR},
      </if>
      <if test="mgcUrl != null" >
        #{mgcUrl,jdbcType=VARCHAR},
      </if>
      <if test="mgcParentNo != null" >
        #{mgcParentNo,jdbcType=VARCHAR},
      </if>
      <if test="mgcStatus != null" >
        #{mgcStatus,jdbcType=VARCHAR},
      </if>
      <if test="createUser != null" >
        #{createUser,jdbcType=VARCHAR},
      </if>
      <if test="createTimestamp != null" >
        #{createTimestamp,jdbcType=DATE},
      </if>
      <if test="updateUser != null" >
        #{updateUser,jdbcType=VARCHAR},
      </if>
      <if test="updateTimestamp != null" >
        #{updateTimestamp,jdbcType=DATE},
      </if>
      <if test="publishArea != null" >
        #{publishArea,jdbcType=VARCHAR},
      </if>
      <if test="publishIssuer != null" >
        #{publishIssuer,jdbcType=VARCHAR},
      </if>
    </trim>
  </insert>
  <select id="countByExample" parameterType="com.cul.culsite.dto.MGoodsDTOCriteria" resultType="java.lang.Integer" >
    <!--
      WARNING - @mbggenerated
      This element is automatically generated by MyBatis Generator, do not modify.
    -->
    select count(*) from M_GOODS_CAT
    <if test="_parameter != null" >
      <include refid="Example_Where_Clause" />
    </if>
  </select>
  <update id="updateByExampleSelective" parameterType="map" >
    <!--
      WARNING - @mbggenerated
      This element is automatically generated by MyBatis Generator, do not modify.
    -->
    update M_GOODS_CAT
    <set >
      <if test="record.mgcId != null" >
        MGC_ID = #{record.mgcId,jdbcType=VARCHAR},
      </if>
      <if test="record.mgcIssuerId != null" >
        MGC_ISSUER_ID = #{record.mgcIssuerId,jdbcType=VARCHAR},
      </if>
      <if test="record.mgcType != null" >
        MGC_TYPE = #{record.mgcType,jdbcType=VARCHAR},
      </if>
      <if test="record.mgcCode != null" >
        MGC_CODE = #{record.mgcCode,jdbcType=VARCHAR},
      </if>
      <if test="record.mgcName != null" >
        MGC_NAME = #{record.mgcName,jdbcType=VARCHAR},
      </if>
      <if test="record.mgcUrl != null" >
        MGC_URL = #{record.mgcUrl,jdbcType=VARCHAR},
      </if>
      <if test="record.mgcParentNo != null" >
        MGC_PARENT_NO = #{record.mgcParentNo,jdbcType=VARCHAR},
      </if>
      <if test="record.mgcStatus != null" >
        MGC_STATUS = #{record.mgcStatus,jdbcType=VARCHAR},
      </if>
      <if test="record.createUser != null" >
        CREATE_USER = #{record.createUser,jdbcType=VARCHAR},
      </if>
      <if test="record.createTimestamp != null" >
        CREATE_TIMESTAMP = #{record.createTimestamp,jdbcType=DATE},
      </if>
      <if test="record.updateUser != null" >
        UPDATE_USER = #{record.updateUser,jdbcType=VARCHAR},
      </if>
      <if test="record.updateTimestamp != null" >
        UPDATE_TIMESTAMP = #{record.updateTimestamp,jdbcType=DATE},
      </if>
      <if test="record.publishArea != null" >
        PUBLISH_AREA = #{record.publishArea,jdbcType=VARCHAR},
      </if>
      <if test="record.publishIssuer != null" >
        PUBLISH_ISSUER = #{record.publishIssuer,jdbcType=VARCHAR},
      </if>
    </set>
    <if test="_parameter != null" >
      <include refid="Update_By_Example_Where_Clause" />
    </if>
  </update>
  <update id="updateByExample" parameterType="map" >
    <!--
      WARNING - @mbggenerated
      This element is automatically generated by MyBatis Generator, do not modify.
    -->
    update M_GOODS_CAT
    set MGC_ID = #{record.mgcId,jdbcType=VARCHAR},
      MGC_ISSUER_ID = #{record.mgcIssuerId,jdbcType=VARCHAR},
      MGC_TYPE = #{record.mgcType,jdbcType=VARCHAR},
      MGC_CODE = #{record.mgcCode,jdbcType=VARCHAR},
      MGC_NAME = #{record.mgcName,jdbcType=VARCHAR},
      MGC_URL = #{record.mgcUrl,jdbcType=VARCHAR},
      MGC_PARENT_NO = #{record.mgcParentNo,jdbcType=VARCHAR},
      MGC_STATUS = #{record.mgcStatus,jdbcType=VARCHAR},
      CREATE_USER = #{record.createUser,jdbcType=VARCHAR},
      CREATE_TIMESTAMP = #{record.createTimestamp,jdbcType=DATE},
      UPDATE_USER = #{record.updateUser,jdbcType=VARCHAR},
      UPDATE_TIMESTAMP = #{record.updateTimestamp,jdbcType=DATE},
      PUBLISH_AREA = #{record.publishArea,jdbcType=VARCHAR},
      PUBLISH_ISSUER = #{record.publishIssuer,jdbcType=VARCHAR}
    <if test="_parameter != null" >
      <include refid="Update_By_Example_Where_Clause" />
    </if>
  </update>
  <update id="updateByPrimaryKeySelective" parameterType="com.cul.culsite.dto.MGoodsDTO" >
    <!--
      WARNING - @mbggenerated
      This element is automatically generated by MyBatis Generator, do not modify.
    -->
    update M_GOODS_CAT
    <set >
      <if test="mgcIssuerId != null" >
        MGC_ISSUER_ID = #{mgcIssuerId,jdbcType=VARCHAR},
      </if>
      <if test="mgcType != null" >
        MGC_TYPE = #{mgcType,jdbcType=VARCHAR},
      </if>
      <if test="mgcCode != null" >
        MGC_CODE = #{mgcCode,jdbcType=VARCHAR},
      </if>
      <if test="mgcName != null" >
        MGC_NAME = #{mgcName,jdbcType=VARCHAR},
      </if>
      <if test="mgcUrl != null" >
        MGC_URL = #{mgcUrl,jdbcType=VARCHAR},
      </if>
      <if test="mgcParentNo != null" >
        MGC_PARENT_NO = #{mgcParentNo,jdbcType=VARCHAR},
      </if>
      <if test="mgcStatus != null" >
        MGC_STATUS = #{mgcStatus,jdbcType=VARCHAR},
      </if>
      <if test="createUser != null" >
        CREATE_USER = #{createUser,jdbcType=VARCHAR},
      </if>
      <if test="createTimestamp != null" >
        CREATE_TIMESTAMP = #{createTimestamp,jdbcType=DATE},
      </if>
      <if test="updateUser != null" >
        UPDATE_USER = #{updateUser,jdbcType=VARCHAR},
      </if>
      <if test="updateTimestamp != null" >
        UPDATE_TIMESTAMP = #{updateTimestamp,jdbcType=DATE},
      </if>
      <if test="publishArea != null" >
        PUBLISH_AREA = #{publishArea,jdbcType=VARCHAR},
      </if>
      <if test="publishIssuer != null" >
        PUBLISH_ISSUER = #{publishIssuer,jdbcType=VARCHAR},
      </if>
    </set>
    where MGC_ID = #{mgcId,jdbcType=VARCHAR}
  </update>
  <update id="updateByPrimaryKey" parameterType="com.cul.culsite.dto.MGoodsDTO" >
    <!--
      WARNING - @mbggenerated
      This element is automatically generated by MyBatis Generator, do not modify.
    -->
    update M_GOODS_CAT
    set MGC_ISSUER_ID = #{mgcIssuerId,jdbcType=VARCHAR},
      MGC_TYPE = #{mgcType,jdbcType=VARCHAR},
      MGC_CODE = #{mgcCode,jdbcType=VARCHAR},
      MGC_NAME = #{mgcName,jdbcType=VARCHAR},
      MGC_URL = #{mgcUrl,jdbcType=VARCHAR},
      MGC_PARENT_NO = #{mgcParentNo,jdbcType=VARCHAR},
      MGC_STATUS = #{mgcStatus,jdbcType=VARCHAR},
      CREATE_USER = #{createUser,jdbcType=VARCHAR},
      CREATE_TIMESTAMP = #{createTimestamp,jdbcType=DATE},
      UPDATE_USER = #{updateUser,jdbcType=VARCHAR},
      UPDATE_TIMESTAMP = #{updateTimestamp,jdbcType=DATE},
      PUBLISH_AREA = #{publishArea,jdbcType=VARCHAR},
      PUBLISH_ISSUER = #{publishIssuer,jdbcType=VARCHAR}
    where MGC_ID = #{mgcId,jdbcType=VARCHAR}
  </update>
</mapper>